daschat_base/__init__.py
daschat_base/base_schemas/__init__.py
daschat_base/base_schemas/slots.py
daschat_base/dc_abc_channel.py
daschat_base/dc_abc_handoff.py
daschat_base/messages.py
daschat_base/schemas.py
daschat_base/types.py
daschat_base/version.py
daschat_base-0.15.10.dist-info/LICENSE
daschat_base-0.15.10.dist-info/WHEEL
daschat_base-0.15.10.dist-info/METADATA
daschat_base-0.15.10.dist-info/RECORD
