Metadata-Version: 2.1
Name: daschat-base
Version: 0.15.10
Summary: Base package for Daschat modules.
Home-page: https://github.com/daschat-io/daschat_base
License: MIT
Author: Abner G Jacobsen
Author-email: abner@apoana.com.br
Requires-Python: >=3.7,<4.0
Classifier: Development Status :: 2 - Pre-Alpha
Classifier: Intended Audience :: Developers
Classifier: License :: OSI Approved :: MIT License
Classifier: Natural Language :: English
Classifier: Programming Language :: Python :: 3
Classifier: Programming Language :: Python :: 3.10
Classifier: Programming Language :: Python :: 3.7
Classifier: Programming Language :: Python :: 3.8
Classifier: Programming Language :: Python :: 3.9
Requires-Dist: cuid (>=0.3,<0.4)
Requires-Dist: loguru (>=0.5.3,<0.6.0)
Requires-Dist: pydantic (>=1.8.2,<2.0.0)
